onlinespreadsheet/__init__.py
onlinespreadsheet/editconfig.py
onlinespreadsheet/loginBlueprint.py
onlinespreadsheet/pareto.py
onlinespreadsheet/profile.py
onlinespreadsheet/propertySelector.py
onlinespreadsheet/tablequery.py
onlinespreadsheet/tablerowselector.py
onlinespreadsheet/version.py
onlinespreadsheet/wtformsutil.py
wd/RecordSync.py
wd/__init__.py
wd/gsimport.py
wd/querydisplay.py
wd/wdbrowser.py
wd/wdgrid.py
wd/wdsearch.py
pyOnlineSpreadsheetEditing-0.2.3.dist-info/LICENSE
pyOnlineSpreadsheetEditing-0.2.3.dist-info/METADATA
pyOnlineSpreadsheetEditing-0.2.3.dist-info/WHEEL
pyOnlineSpreadsheetEditing-0.2.3.dist-info/top_level.txt
pyOnlineSpreadsheetEditing-0.2.3.dist-info/RECORD
