Metadata-Version: 2.1
Name: pyOnlineSpreadsheetEditing
Version: 0.2.3
Summary: python Online SpreadSheet Editing tool with configurable enhancer/importer and check phase
Home-page: http://wiki.bitplan.com/index.php/pyOnlineSpreadsheetEditing
Download-URL: https://github.com/WolfgangFahl/pyOnlineSpreadsheetEditing
Author: Wolfgang Fahl
Author-email: wf@bitplan.com
License: Apache
Project-URL: Code, https://github.com/WolfgangFahl/pyOnlineSpreadsheetEditing
Project-URL: Issue tracker, https://github.com/WolfgangFahl/pyOnlineSpreadsheetEditing/issues
Classifier: Programming Language :: Python
Classifier: Programming Language :: Python :: 3.8
Classifier: Programming Language :: Python :: 3.9
Classifier: Programming Language :: Python :: 3.10
License-File: LICENSE
Requires-Dist: py-3rdparty-mediawiki (>=0.8.1)
Requires-Dist: ruamel.yaml
Requires-Dist: justpy (>=0.12.1)
Requires-Dist: python-dateutil
Requires-Dist: pyGenericSpreadSheet (>=0.2.4)
Requires-Dist: pyJustpyWidgets (>=0.1.13)
